litemort/LiteMORT.dll
litemort/LiteMORT.py
litemort/LiteMORT_EDA.py
litemort/LiteMORT_ERA.py
litemort/LiteMORT_hyppo.py
litemort/LiteMORT_preprocess.py
litemort/LiteMORT_problems.py
litemort/LiteMORT_regression.py
litemort/LiteMORT_time.py
litemort/__init__.py
litemort/__version__.py
litemort/compat.py
litemort/libLiteMORT.so
litemort/libpath.py
litemort-0.1.18.data/data/litemort/LiteMORT.dll
litemort-0.1.18.data/data/litemort/libLiteMORT.so
litemort-0.1.18.dist-info/LICENSE
litemort-0.1.18.dist-info/METADATA
litemort-0.1.18.dist-info/WHEEL
litemort-0.1.18.dist-info/top_level.txt
litemort-0.1.18.dist-info/RECORD
